.gitignore
.travis.yml
AUTHORS
CHANGELOG
DEVELOPERS.txt
MANIFEST.in
NEWS
NEWS_0.9
NOTES
PLUGIN_API_CHANGES.txt
README.BDIST_RPM
README.md
README.txt
TODO
TODO_0_9
distribute_setup.py
install-rpm.sh
lgpl.txt
nosetests.1
requirements.txt
run_tests.sh
selftest.py
setup.cfg
setup.cfg.release
setup.py
tickets.csv
tickets.rss
tox.ini
.github/workflows/py33.yml
.github/workflows/tox-gh.yml
bin/nosetests
doc/Makefile
doc/api.rst
doc/conf.py
doc/contributing.rst
doc/developing.rst
doc/doc_tests
doc/docstring.py
doc/finding_tests.rst
doc/further_reading.rst
doc/index.html
doc/index.rst
doc/man.rst
doc/more_info.rst
doc/news.rst
doc/plugins.rst
doc/rtd-requirements.txt
doc/setuptools_integration.rst
doc/testing.rst
doc/testing_tools.rst
doc/usage.rst
doc/writing_tests.rst
doc/.static/nose.css
doc/.templates/index.html
doc/.templates/indexsidebar.html
doc/.templates/layout.html
doc/.templates/page.html
doc/api/commands.rst
doc/api/config.rst
doc/api/core.rst
doc/api/importer.rst
doc/api/inspector.rst
doc/api/loader.rst
doc/api/plugin_manager.rst
doc/api/proxy.rst
doc/api/result.rst
doc/api/selector.rst
doc/api/suite.rst
doc/api/test_cases.rst
doc/api/twistedtools.rst
doc/api/util.rst
doc/doc_tests/test_addplugins/test_addplugins.rst
doc/doc_tests/test_addplugins/support/test.py
doc/doc_tests/test_addplugins/support/test.pyc
doc/doc_tests/test_addplugins/support/__pycache__/test.cpython-310.pyc
doc/doc_tests/test_addplugins/support/__pycache__/test.cpython-311.pyc
doc/doc_tests/test_addplugins/support/__pycache__/test.cpython-37.pyc
doc/doc_tests/test_allmodules/test_allmodules.rst
doc/doc_tests/test_allmodules/support/mod.py
doc/doc_tests/test_allmodules/support/mod.pyc
doc/doc_tests/test_allmodules/support/test.py
doc/doc_tests/test_allmodules/support/test.pyc
doc/doc_tests/test_allmodules/support/__pycache__/mod.cpython-310.pyc
doc/doc_tests/test_allmodules/support/__pycache__/mod.cpython-311.pyc
doc/doc_tests/test_allmodules/support/__pycache__/mod.cpython-37.pyc
functional_tests/support/ep/Some_plugin.egg-info/PKG-INFO
functional_tests/support/ep/Some_plugin.egg-info/SOURCES.txt
functional_tests/support/ep/Some_plugin.egg-info/dependency_links.txt
functional_tests/support/ep/Some_plugin.egg-info/entry_points.txt
functional_tests/support/ep/Some_plugin.egg-info/top_level.txt
functional_tests/support/issue191/UNKNOWN.egg-info/PKG-INFO
functional_tests/support/issue191/UNKNOWN.egg-info/SOURCES.txt
functional_tests/support/issue191/UNKNOWN.egg-info/dependency_links.txt
functional_tests/support/issue191/UNKNOWN.egg-info/top_level.txt
functional_tests/support/issue191/issue191.egg-info/PKG-INFO
functional_tests/support/issue191/issue191.egg-info/SOURCES.txt
functional_tests/support/issue191/issue191.egg-info/dependency_links.txt
functional_tests/support/issue191/issue191.egg-info/top_level.txt
nose3.egg-info/PKG-INFO
nose3.egg-info/SOURCES.txt
nose3.egg-info/dependency_links.txt
nose3.egg-info/entry_points.txt
nose3.egg-info/not-zip-safe
nose3.egg-info/top_level.txt
