Metadata-Version: 2.1
Name: nose3
Version: 1.3.8
Summary: nose extends unittest to make testing easier
Home-page: https://github.com/jayvdb/nose3
Author: Jason Pellerin
Author-email: jpellerin+nose@gmail.com
License: GNU LGPL
Keywords: test unittest doctest automatic discovery
Classifier: Development Status :: 5 - Production/Stable
Classifier: Intended Audience :: Developers
Classifier: License :: OSI Approved :: GNU Library or Lesser General Public License (LGPL)
Classifier: Natural Language :: English
Classifier: Operating System :: OS Independent
Classifier: Programming Language :: Python
Classifier: Programming Language :: Python :: 3
Classifier: Topic :: Software Development :: Testing
License-File: AUTHORS
